seu_3d/__init__.py
seu_3d/_umap_selection.py
seu_3d/_utils.py
seu_3d/display.py
seu_3d/embryo.py
seu_3d/load.py
seu_3d/napari.yaml
seu_3d-1.1.16.dist-info/METADATA
seu_3d-1.1.16.dist-info/WHEEL
seu_3d-1.1.16.dist-info/entry_points.txt
seu_3d-1.1.16.dist-info/top_level.txt
seu_3d-1.1.16.dist-info/RECORD
