Metadata-Version: 2.4
Name: seu-3d
Version: 1.1.16
Summary: 3d spatial visualization napari plugin
Author-email: pxieLab <220242543@seu.edu.cn>
Project-URL: Homepage, https://github.com/DingAnZhong/SEU-3D
Classifier: Framework :: napari
Classifier: Programming Language :: Python :: 3
Classifier: Operating System :: Microsoft :: Windows
Requires-Python: >=3.10
